coronacaster/__init__.py
coronacaster/data.py
coronacaster/forecast.py
coronacaster/models.py
coronacaster/plots.py
coronacaster/utils.py
Coronacaster-0.2.0.dist-info/METADATA
Coronacaster-0.2.0.dist-info/WHEEL
Coronacaster-0.2.0.dist-info/top_level.txt
Coronacaster-0.2.0.dist-info/RECORD
