Metadata-Version: 2.1
Name: Coronacaster
Version: 0.2.0
Summary: Probabilistic Programming Forecasting for COVID-19 Cases
Home-page: http://autonom.io
Author: Mikko Kotila
Author-email: mailme@mikkokotila.com
Maintainer: Mikko Kotila
Maintainer-email: mailme@mikkokotila.com
License: MIT
Download-URL: https://github.com/autonomio/coronacast/
Platform: UNKNOWN
Classifier: Intended Audience :: Science/Research
Classifier: Programming Language :: Python :: 3.6
Classifier: Programming Language :: Python :: 3.7
Classifier: Programming Language :: Python :: 3.8
Classifier: License :: OSI Approved :: MIT License
Classifier: Topic :: Scientific/Engineering :: Human Machine Interfaces
Classifier: Topic :: Scientific/Engineering :: Mathematics
Classifier: Operating System :: POSIX
Classifier: Operating System :: Unix
Classifier: Operating System :: MacOS
Classifier: Operating System :: Microsoft :: Windows :: Windows 10
Requires-Dist: pymc3
Requires-Dist: matplotlib
Requires-Dist: seaborn
Requires-Dist: pandas
Requires-Dist: numpy
Requires-Dist: xlrd
